py_typewriter_sse-0.3.0.dist-info/licenses/LICENSE
typewriter/__init__.py
py_typewriter_sse-0.3.0.dist-info/METADATA
py_typewriter_sse-0.3.0.dist-info/WHEEL
py_typewriter_sse-0.3.0.dist-info/top_level.txt
py_typewriter_sse-0.3.0.dist-info/RECORD
