Metadata-Version: 2.4
Name: py-typewriter-sse
Version: 0.3.0
Summary: 一个简单、灵活的库，用于在终端模拟打字机输出效果。
Author-email: orxvan <orxvan@gmail.com>
Project-URL: Homepage, https://github.com/orxvan/py-typewriter
Project-URL: Bug Tracker, https://github.com/orxvan/py-typewriter/issues
Keywords: typewriter,terminal,cli,effect,typing,sse
Classifier: Development Status :: 4 - Beta
Classifier: Programming Language :: Python :: 3
Classifier: License :: OSI Approved :: MIT License
Classifier: Operating System :: OS Independent
Classifier: Intended Audience :: Developers
Classifier: Topic :: Terminals
Classifier: Topic :: Software Development :: Libraries :: Python Modules
Requires-Python: >=3.7
License-File: LICENSE
Dynamic: license-file
